{"alpha":[1,1,1,1,1,1,1,1,1,1,1,1,1,1,1,1,1,1,1,1,1,1,1,1,1,1,1,1,1,1,1,1,1,1,1,1,1,1,1,1],"tw":[{"words":["la","des","em","les","da","le","se","en","na","para","du","os","à","das","um","mulheres","est","por","como","france","es","uma","au","brazil","french","par","une","paris","dos","femmes","ou","dans","ce","sur","mais","qui","brazilian","pas","entre","nos","ne","il","rio","feministas","mas","sobre","ser","social","si","sa"],"weights":[-3.1037,-3.276,-3.2961,-3.3427,-3.3455,-3.3863,-3.6121,-3.6415,-3.6622,-3.8248,-3.8253,-3.985,-4.0044,-4.1421,-4.1815,-4.1955,-4.197,-4.238,-4.2434,-4.2662,-4.2678,-4.2855,-4.3002,-4.3068,-4.3916,-4.3952,-4.3997,-4.4007,-4.4052,-4.4071,-4.4089,-4.4135,-4.4773,-4.4852,-4.5287,-4.6152,-4.6152,-4.6311,-4.6962,-4.7286,-4.7426,-4.7477,-4.9081,-4.9835,-5.1384,-5.1538,-5.2406,-5.3037,-5.3426,-5.4028]},{"words":["art","media","film","body","culture","images","cultural","female","image","beauty","bodies","space","artists","popular","technology","internet","performance","visual","films","music","play","sport","site","artist","girl","web","audience","video","television","computer","sports","public","male","girls","online","hair","figure","production","information","form","representation","representations","print","news","magazine","woman","technologies","arts","digital","scene"],"weights":[-3.878,-4.0791,-4.096,-4.3472,-4.505,-4.5273,-4.7275,-4.7424,-4.76,-4.8673,-4.8833,-4.901,-4.9022,-4.9329,-4.9806,-5.0426,-5.0439,-5.166,-5.1699,-5.2107,-5.2138,-5.3208,-5.3208,-5.3816,-5.3858,-5.4203,-5.4496,-5.46,-5.4652,-5.4952,-5.5429,-5.55,-5.5724,-5.5834,-5.6356,-5.6372,-5.645,-5.6672,-5.6721,-5.6761,-5.6769,-5.6883,-5.6892,-5.6999,-5.7208,-5.7362,-5.7492,-5.773,-5.7864,-5.7946]},{"words":["gender","feminist","power","identity","discourse","politics","difference","social","cultural","practices","theory","feminism","political","identities","discourses","analysis","terms","relations","experience","subject","critical","context","agency","culture","language","gendered","practice","experiences","resistance","critique","understanding","construction","sense","butler","argues","relation","forms","multiple","notion","dominant","meaning","category","space","discursive","categories","subjectivity","subjects","foucault","specific","concept"],"weights":[-3.5975,-3.939,-4.1331,-4.1404,-4.5066,-4.6761,-4.7138,-4.7579,-4.852,-4.8648,-4.9151,-4.9803,-5.0029,-5.0603,-5.0617,-5.0766,-5.0872,-5.1124,-5.1363,-5.1892,-5.2732,-5.2991,-5.326,-5.3285,-5.3702,-5.3855,-5.3944,-5.4433,-5.4854,-5.5368,-5.5466,-5.5684,-5.5752,-5.5957,-5.6206,-5.6278,-5.6519,-5.6543,-5.6736,-5.6892,-5.6918,-5.7006,-5.7066,-5.7216,-5.7242,-5.7696,-5.7851,-5.8051,-5.8208,-5.8258]},{"words":["body","human","disability","social","female","nature","people","male","bodies","physical","disabled","biological","natural","culture","disabilities","animals","animal","behavior","society","sex","psychology","differences","cultural","males","genetic","psychological","bodily","humans","females","mental","life","model","species","experience","york","control","biology","brain","ability","person","difference","world","evolution","system","normal","role","evolutionary","individual","development","intelligence"],"weights":[-3.492,-3.8215,-4.0039,-4.1556,-4.216,-4.228,-4.4035,-4.431,-4.4532,-4.5887,-4.5977,-4.6439,-4.7995,-4.9111,-4.961,-4.9711,-4.983,-5.0157,-5.0188,-5.026,-5.1331,-5.2297,-5.238,-5.2689,-5.2996,-5.3696,-5.381,-5.4115,-5.4154,-5.4415,-5.4669,-5.5338,-5.5473,-5.5975,-5.6102,-5.6183,-5.6613,-5.6766,-5.6921,-5.7258,-5.7348,-5.7948,-5.8025,-5.8272,-5.8627,-5.8751,-5.8867,-5.8973,-5.8995,-5.9478]},{"words":["children","child","mothers","mother","girls","parents","family","families","motherhood","school","girl","fathers","father","boys","mothering","social","maternal","parent","daughter","age","daughters","single","parenting","adult","home","childhood","support","youth","parental","adoption","life","baby","birth","son","time","cultural","society","lives","middle","adults","adolescent","role","teen","kids","emotional","schools","boy","fatherhood","study","class"],"weights":[-2.3306,-2.8092,-2.9444,-3.1219,-3.2875,-3.5695,-3.5947,-4.0363,-4.1289,-4.3072,-4.3876,-4.4451,-4.4908,-4.5274,-4.5855,-4.7565,-4.778,-4.8194,-4.8819,-5.0222,-5.0402,-5.0728,-5.0913,-5.1199,-5.1892,-5.1914,-5.2071,-5.2294,-5.302,-5.3039,-5.3722,-5.3783,-5.4299,-5.4307,-5.48,-5.5148,-5.5492,-5.5824,-5.6117,-5.6125,-5.6711,-5.7773,-5.7824,-5.8027,-5.834,-5.8663,-5.8784,-5.8817,-5.8817,-5.8996]},{"words":["american","york","press","history","century","university","ed","life","america","woman","mary","home","nineteenth","john","chicago","city","house","vol","public","time","england","elizabeth","day","wrote","letter","boston","ing","papers","journal","william","smith","historical","james","letters","found","jane","robert","david","library","charles","cambridge","brown","late","free","virginia","ann","times","spring","twentieth","george"],"weights":[-3.6794,-3.8795,-4.2192,-4.271,-4.2728,-4.4312,-4.737,-4.7477,-4.8239,-4.9349,-4.9563,-5.0215,-5.0365,-5.0606,-5.072,-5.1265,-5.1578,-5.2211,-5.2994,-5.368,-5.4237,-5.4482,-5.5238,-5.5464,-5.5571,-5.5678,-5.5851,-5.5909,-5.6127,-5.6786,-5.7051,-5.7084,-5.7236,-5.733,-5.7417,-5.7679,-5.8011,-5.8333,-5.8445,-5.8475,-5.8498,-5.8559,-5.8774,-5.9026,-5.9042,-5.905,-5.9235,-5.9541,-5.9625,-5.9633]},{"words":["women","chinese","japanese","china","japan","party","female","period","woman","political","society","time","soviet","male","korean","government","revolution","modern","western","national","english","club","nation","russian","history","european","century","british","communist","system","journal","official","ibid","education","country","public","korea","russia","late","tokyo","irish","europe","foreign","socialist","population","imperial","law","established","republic","britain"],"weights":[-2.5453,-3.9888,-4.1895,-4.2799,-4.302,-4.6978,-4.7361,-4.8448,-4.9135,-4.9565,-5.0606,-5.1408,-5.149,-5.149,-5.1507,-5.1708,-5.2707,-5.3009,-5.3077,-5.3306,-5.3376,-5.3468,-5.4254,-5.4583,-5.499,-5.5233,-5.5284,-5.5431,-5.5659,-5.5829,-5.5883,-5.5892,-5.6066,-5.6225,-5.6588,-5.6735,-5.6874,-5.6935,-5.6985,-5.7128,-5.7569,-5.7841,-5.8633,-5.8645,-5.8814,-5.8887,-5.8998,-5.9136,-5.9287,-5.9481]},{"words":["woman","love","life","world","mother","death","time","language","sense","body","words","desire","experience","story","nature","beauvoir","father","power","rich","memory","irigaray","poem","human","writes","truth","relationship","moment","form","mind","voice","word","image","meaning","past","reality","subject","hand","poetry","consciousness","act","living","vision","means","space","makes","ing","real","figure","future","takes"],"weights":[-3.9979,-4.0793,-4.1628,-4.2255,-4.5078,-4.7948,-4.8909,-4.9721,-5.0943,-5.1036,-5.1314,-5.1984,-5.2599,-5.2894,-5.3446,-5.3566,-5.4082,-5.478,-5.4823,-5.497,-5.512,-5.6088,-5.618,-5.6354,-5.6404,-5.6409,-5.656,-5.6792,-5.7221,-5.7239,-5.7725,-5.7756,-5.7909,-5.8013,-5.8078,-5.8156,-5.8209,-5.8322,-5.8403,-5.843,-5.8546,-5.8614,-5.8816,-5.9058,-5.9152,-5.9388,-5.9418,-5.956,-5.956,-5.9621]},{"words":["feminist","science","knowledge","research","studies","theory","social","scientific","feminism","field","theories","scientists","sciences","technology","world","feminists","questions","philosophy","scholars","standpoint","methods","theoretical","epistemology","harding","scholarship","critical","nature","political","inquiry","academic","practice","analysis","issues","question","intellectual","method","perspectives","study","approaches","disciplines","approach","haraway","assumptions","gender","project","perspective","history","traditional","objectivity","critique"],"weights":[-2.8357,-3.1575,-3.7928,-3.8686,-3.9805,-3.9918,-4.0216,-4.3928,-4.6213,-4.7746,-4.8852,-4.9603,-5.0137,-5.0788,-5.0891,-5.0921,-5.12,-5.1512,-5.1679,-5.1768,-5.2756,-5.285,-5.2996,-5.411,-5.437,-5.4556,-5.4583,-5.4599,-5.4745,-5.5016,-5.5118,-5.5226,-5.5388,-5.5529,-5.6013,-5.6038,-5.6264,-5.636,-5.6379,-5.6528,-5.7522,-5.7682,-5.7763,-5.7919,-5.7949,-5.8032,-5.807,-5.8086,-5.8247,-5.827]},{"words":["religious","religion","feminist","church","god","christian","women","theology","spiritual","studies","catholic","journal","theological","faith","world","goddess","tradition","life","traditions","spirituality","power","experience","christianity","womanist","religions","biblical","christ","mary","human","divine","liberation","community","bible","jesus","male","churches","sacred","scholars","ritual","spirit","patriarchal","ibid","theologians","press","jewish","daly","feminists","buddhist","culture","vision"],"weights":[-3.3927,-3.4468,-3.5697,-3.7774,-3.8486,-3.8708,-4.1979,-4.2499,-4.7115,-4.731,-4.788,-4.7958,-4.8942,-4.9774,-5.0013,-5.0064,-5.014,-5.0714,-5.1374,-5.1842,-5.257,-5.2675,-5.2835,-5.2915,-5.2929,-5.3231,-5.3413,-5.373,-5.3818,-5.3975,-5.402,-5.4126,-5.4264,-5.4674,-5.5126,-5.5168,-5.5399,-5.5495,-5.6371,-5.6486,-5.6641,-5.6661,-5.6779,-5.7814,-5.7858,-5.7913,-5.8037,-5.8104,-5.8427,-5.8533]},{"words":["2003","2004","2005","2006","2002","gender","2007","http","2008","www","2009","2010","2001","2000","university","2011","gendered","org","2012","press","2013","accessed","1999","social","research","journal","1998","review","york","html","article","society","al","2014","studies","practices","masculinity","pdf","1997","online","2015","uk","focus","based","public","study","masculinities","united","doi","site"],"weights":[-3.4039,-3.4363,-3.4589,-3.4941,-3.5195,-3.586,-3.6089,-3.7293,-3.7339,-3.752,-3.7725,-3.8923,-3.9104,-3.9721,-4.2007,-4.3756,-4.4202,-4.4382,-4.5136,-4.5329,-4.7105,-4.722,-4.7491,-4.7653,-4.7782,-4.8705,-5.015,-5.0911,-5.1374,-5.1765,-5.213,-5.2171,-5.2782,-5.2952,-5.3481,-5.3685,-5.4428,-5.4725,-5.5081,-5.6043,-5.6287,-5.6315,-5.6429,-5.6529,-5.72,-5.7224,-5.7813,-5.8536,-5.8642,-5.8651]},{"words":["women","woman","female","male","press","studies","york","university","1982","1983","1981","1980","1985","1984","1987","1979","1986","ed","roles","sex","society","signs","1978","1975","role","1977","1976","1974","american","1988","change","lives","history","social","1973","tion","power","status","review","experience","1989","traditional","study","development","1970","1972","journal","mary","perspective","con"],"weights":[-1.0403,-3.6858,-4.1798,-4.2186,-4.3762,-4.4046,-4.448,-4.5057,-4.6728,-4.6769,-4.7062,-4.7102,-4.7479,-4.7938,-4.8203,-4.8375,-4.9182,-4.9729,-4.9937,-4.9942,-4.998,-5.0077,-5.0243,-5.044,-5.1957,-5.235,-5.2504,-5.2556,-5.3383,-5.3723,-5.4177,-5.4288,-5.4948,-5.5193,-5.527,-5.5532,-5.5874,-5.5913,-5.6153,-5.6466,-5.6584,-5.7073,-5.7789,-5.7984,-5.8586,-5.8624,-5.8895,-5.9066,-5.9234,-6.0131]},{"words":["black","white","race","american","class","african","racial","color","racism","americans","people","asian","blacks","ethnic","whites","racist","oppression","community","social","america","united","identity","privilege","middle","york","collins","minority","whiteness","skin","poor","culture","anti","smith","history","cultural","slavery","ethnicity","experiences","sexism","negro","afro","hill","economic","south","hooks","racialized","families","poverty","brown","struggle"],"weights":[-2.1951,-2.5922,-2.8316,-3.1376,-3.3566,-3.4443,-3.5512,-3.6024,-3.9222,-4.3008,-4.4089,-4.5838,-4.6468,-4.8013,-4.8286,-4.9993,-5.1147,-5.2077,-5.2132,-5.2379,-5.2417,-5.2427,-5.2613,-5.2696,-5.2715,-5.4899,-5.4942,-5.4978,-5.5114,-5.5467,-5.5754,-5.5807,-5.5961,-5.6104,-5.634,-5.6689,-5.7074,-5.7158,-5.7737,-5.8517,-5.8657,-5.9036,-5.9506,-5.9739,-6.0141,-6.0234,-6.0646,-6.1212,-6.135,-6.1361]},{"words":["women","labor","employment","job","gender","jobs","percent","workers","female","force","market","time","male","wage","business","occupational","workplace","pay","management","wages","occupations","paid","career","discrimination","employees","earnings","sex","professional","positions","employed","employers","managers","segregation","hours","industry","lower","company","organization","gap","worth","opportunities","service","organizational","organizations","status","industrial","participation","level","low","economic"],"weights":[-2.8542,-3.51,-4.0853,-4.1254,-4.1921,-4.1936,-4.2643,-4.3649,-4.5404,-4.6033,-4.6634,-4.6788,-4.6928,-4.7157,-4.7833,-4.9699,-4.9849,-5.0142,-5.0885,-5.1534,-5.1728,-5.1908,-5.1958,-5.2148,-5.2265,-5.2464,-5.2683,-5.3099,-5.3244,-5.3353,-5.3679,-5.4128,-5.4422,-5.4629,-5.4683,-5.4695,-5.5507,-5.6188,-5.6307,-5.6321,-5.6321,-5.6357,-5.6428,-5.6514,-5.6536,-5.6681,-5.6866,-5.6933,-5.7085,-5.7324]},{"words":["family","marriage","women","husband","wife","married","wives","woman","husbands","families","home","household","male","domestic","children","status","roles","traditional","society","life","power","relationships","role","father","female","time","divorce","social","control","relationship","house","marital","marriages","law","property","marry","couples","relations","kin","change","authority","mother","patriarchal","housework","kinship","economic","cultural","daughters","support","norms"],"weights":[-2.6484,-3.3114,-3.4462,-3.7868,-3.9962,-4.2636,-4.2794,-4.3518,-4.3945,-4.3945,-4.4941,-4.5654,-4.6871,-4.7492,-4.8011,-4.8179,-4.8634,-4.9035,-4.934,-4.9421,-4.9622,-4.9629,-4.964,-5.0016,-5.0345,-5.0424,-5.0832,-5.0951,-5.0955,-5.1005,-5.1804,-5.2092,-5.2288,-5.3275,-5.4146,-5.4588,-5.5189,-5.5386,-5.5754,-5.6183,-5.6296,-5.675,-5.6802,-5.6846,-5.7211,-5.7351,-5.7429,-5.8048,-5.8575,-5.8681]},{"words":["moral","ethics","human","theory","feminist","view","philosophy","reason","respect","ethical","autonomy","account","person","individual","sense","claim","hypatia","values","press","question","action","responsibility","argument","understanding","nature","claims","philosophical","ed","world","people","persons","individuals","simply","ideal","justice","freedom","feminists","relationships","oppression","virtue","thinking","conception","trust","concept","requires","argue","means","situation","makes","position"],"weights":[-3.8578,-4.4794,-4.7822,-4.8324,-4.8652,-5.013,-5.0748,-5.1603,-5.2195,-5.2253,-5.2972,-5.3242,-5.3393,-5.3681,-5.4122,-5.4297,-5.4816,-5.5122,-5.5347,-5.5525,-5.5642,-5.5817,-5.5883,-5.6354,-5.6515,-5.6716,-5.7083,-5.7129,-5.7319,-5.7372,-5.7376,-5.7463,-5.7654,-5.7769,-5.7784,-5.8037,-5.8083,-5.8187,-5.8435,-5.8575,-5.863,-5.869,-5.875,-5.8756,-5.8811,-5.8817,-5.9161,-5.9376,-5.9429,-5.9488]},{"words":["violence","women","rape","law","abuse","sexual","rights","legal","victims","prison","police","court","domestic","human","justice","crime","trafficking","criminal","victim","violent","survivors","system","assault","battered","trauma","protection","physical","prisoners","laws","act","woman","public","report","control","courts","crimes","raped","prisons","acts","fear","male","forced","forms","evidence","social","based","safety","incest","memory","abused"],"weights":[-2.7099,-3.1782,-3.6798,-3.7281,-3.9264,-3.9692,-3.9849,-4.0215,-4.3429,-4.3543,-4.4359,-4.4875,-4.6545,-4.7061,-4.7166,-4.7539,-4.7761,-4.8438,-4.867,-5.0832,-5.1015,-5.204,-5.21,-5.234,-5.2672,-5.3063,-5.3966,-5.4143,-5.4277,-5.4392,-5.4808,-5.4851,-5.5096,-5.5169,-5.5213,-5.5712,-5.5996,-5.6052,-5.6353,-5.6664,-5.6897,-5.7171,-5.7371,-5.7371,-5.7417,-5.8033,-5.8063,-5.8161,-5.8261,-5.8504]},{"words":["women","south","africa","african","gender","agenda","rights","government","cape","southern","national","rural","apartheid","town","issues","access","people","education","equality","male","society","kenya","customary","structures","nigeria","natal","commission","africans","constitution","zimbabwe","country","culture","local","terms","uganda","organisations","traditional","1998","centre","struggle","anc","ghana","1999","based","role","parliament","2000","issue","process","article"],"weights":[-2.5112,-2.7292,-2.8631,-2.9746,-3.5692,-3.9033,-4.7176,-4.7737,-4.8585,-4.8803,-4.9041,-5.0149,-5.0947,-5.1322,-5.139,-5.3046,-5.3276,-5.3434,-5.3557,-5.4308,-5.4603,-5.4715,-5.5023,-5.5157,-5.5175,-5.5312,-5.5658,-5.5744,-5.6205,-5.6346,-5.6604,-5.6805,-5.7064,-5.7108,-5.7454,-5.7546,-5.7684,-5.7754,-5.7861,-5.7884,-5.792,-5.8004,-5.8028,-5.8052,-5.81,-5.8572,-5.8611,-5.8611,-5.8675,-5.8961]},{"words":["press","university","1993","1995","1994","1990","gender","1992","1991","1997","1996","york","1998","1989","1999","2000","1988","1987","ed","eds","2001","london","paper","routledge","1986","society","edited","politics","1985","cambridge","1984","oxford","gendered","california","cultural","chicago","1983","martin","perspectives","books","berkeley","boston","1982","theory","philadelphia","1980s","al","culture","temple","1990s"],"weights":[-2.903,-3.0448,-3.2531,-3.2675,-3.292,-3.3466,-3.3517,-3.3589,-3.4269,-3.4827,-3.4946,-3.5245,-3.6673,-3.7655,-3.845,-4.0208,-4.0781,-4.1727,-4.3445,-4.6441,-4.6517,-4.7544,-4.7742,-4.809,-4.8147,-4.8507,-4.9048,-5.0296,-5.1152,-5.1412,-5.1602,-5.3041,-5.319,-5.4526,-5.4988,-5.5,-5.5574,-5.6042,-5.699,-5.6997,-5.7071,-5.7424,-5.7734,-5.7989,-5.7989,-5.8929,-5.93,-5.9724,-6.04,-6.0671]},{"words":["care","caring","social","services","family","home","nursing","health","elderly","people","time","paid","service","clients","dependency","term","caregivers","labor","relationships","child","age","provide","support","families","aging","caregiving","relationship","children","responsibility","nurses","providers","personal","emotional","life","society","workers","responsibilities","day","client","policy","welfare","unpaid","resources","activities","assistance","dependent","homes","quality","nurse","private"],"weights":[-2.0869,-3.8521,-4.0794,-4.1569,-4.2399,-4.3119,-4.6457,-4.6812,-4.6816,-4.7014,-4.7216,-4.7473,-4.7595,-4.7857,-4.9117,-4.9745,-5.0005,-5.0836,-5.1099,-5.1377,-5.1384,-5.1446,-5.1544,-5.2067,-5.2082,-5.2381,-5.2419,-5.3008,-5.3139,-5.3196,-5.3354,-5.3421,-5.3566,-5.3967,-5.4012,-5.403,-5.4201,-5.4649,-5.4764,-5.4793,-5.5248,-5.5421,-5.5525,-5.5598,-5.5746,-5.6497,-5.66,-5.6693,-5.6835,-5.7099]},{"words":["la","en","el","los","las","mexican","latin","mexico","del","chicana","con","se","spanish","latina","puerto","una","por","para","mujeres","es","al","chicano","como","lo","su","cuba","america","cuban","social","rican","maria","chicanas","angeles","mujer","argentina","latinas","hispanic","american","peru","latino","sus","chile","sobre","son","ha","san","ser","si","texas","sin"],"weights":[-2.2994,-2.8083,-2.8869,-3.0933,-3.281,-3.4649,-3.5233,-3.6348,-3.7989,-3.9271,-3.9583,-4.0605,-4.0783,-4.1252,-4.1374,-4.2104,-4.239,-4.2859,-4.2911,-4.3275,-4.3896,-4.4359,-4.5557,-4.5729,-4.5859,-4.5947,-4.5991,-4.617,-4.7195,-4.7326,-4.7336,-4.7357,-4.8327,-4.9143,-5.022,-5.037,-5.0877,-5.132,-5.138,-5.1396,-5.1564,-5.1689,-5.2729,-5.2816,-5.36,-5.3948,-5.3948,-5.4247,-5.496,-5.5472]},{"words":["health","hiv","aids","medical","research","women","breast","cancer","risk","treatment","disease","medicine","patients","al","care","patient","public","drug","journal","prevention","illness","clinical","feeding","breastfeeding","bioethics","mental","hospital","physicians","infection","services","diseases","doctors","information","positive","infant","international","factors","healthy","drugs","therapy","epidemic","mortality","milk","related","practice","social","national","community","rates","professionals"],"weights":[-2.3253,-3.5775,-3.6099,-3.6287,-4.1116,-4.2965,-4.3373,-4.3403,-4.4517,-4.472,-4.5031,-4.5774,-4.7339,-4.8193,-4.8537,-4.8791,-4.9161,-5.0578,-5.1017,-5.1161,-5.1267,-5.1602,-5.1651,-5.1968,-5.2722,-5.3792,-5.4171,-5.4597,-5.4914,-5.4965,-5.4982,-5.5499,-5.581,-5.5941,-5.595,-5.6432,-5.6561,-5.6621,-5.6948,-5.7021,-5.7201,-5.7222,-5.7416,-5.7482,-5.757,-5.7659,-5.7659,-5.793,-5.8092,-5.8151]},{"words":["book","writing","history","literature","text","literary","writers","century","narrative","books","story","texts","life","readers","reading","female","author","stories","read","essays","culture","fiction","written","reader","essay","authors","modern","historical","volume","writer","published","press","review","chapter","english","lives","collection","critical","introduction","novels","criticism","woolf","narratives","american","nineteenth","woman","writings","contemporary","language","study"],"weights":[-3.6844,-4.083,-4.2058,-4.2746,-4.3698,-4.4245,-4.4487,-4.4686,-4.551,-4.5764,-4.6233,-4.6693,-4.6879,-4.7158,-4.7269,-4.7849,-4.8163,-4.8438,-4.8657,-4.8799,-4.947,-4.967,-5.0169,-5.0182,-5.0487,-5.0894,-5.1427,-5.1586,-5.1649,-5.2674,-5.2998,-5.3024,-5.3288,-5.343,-5.3924,-5.4181,-5.4558,-5.4583,-5.4709,-5.4785,-5.4837,-5.5434,-5.5566,-5.561,-5.5972,-5.6018,-5.6504,-5.6731,-5.69,-5.7046]},{"words":["class","social","labor","economic","relations","society","production","power","system","capitalism","political","world","capitalist","analysis","middle","economy","structure","control","oppression","gender","patriarchy","capital","ideology","inequality","reproduction","process","historical","life","socialist","material","division","forms","conditions","domination","market","struggle","societies","theory","marxist","structures","london","position","review","means","classes","ideological","domestic","marx","exploitation","family"],"weights":[-2.9162,-3.2289,-3.87,-4.0651,-4.1805,-4.3183,-4.5654,-4.5974,-4.6287,-4.6706,-4.7106,-4.7504,-4.7523,-4.899,-4.9276,-4.9463,-5.044,-5.0617,-5.0977,-5.1112,-5.2197,-5.2201,-5.221,-5.2324,-5.335,-5.3443,-5.3567,-5.3789,-5.3933,-5.4011,-5.4281,-5.4542,-5.4642,-5.4681,-5.4924,-5.5561,-5.5721,-5.5921,-5.5921,-5.5947,-5.5947,-5.6348,-5.6454,-5.6676,-5.6724,-5.6806,-5.6953,-5.6974,-5.708,-5.7144]},{"words":["women","feminist","movement","feminism","political","feminists","activists","organizations","movements","activism","politics","organization","issues","rights","conference","national","organizing","radical","activist","collective","wave","liberation","struggle","anti","action","issue","consciousness","support","local","struggles","move","change","organized","leaders","coalition","leadership","solidarity","1970s","time","ing","efforts","ment","left","personal","nwsa","pro","tion","1980s","protest","party"],"weights":[-2.2483,-3.1078,-3.2439,-3.7143,-3.9315,-3.9856,-4.2496,-4.2702,-4.4073,-4.4557,-4.5693,-4.6096,-4.6606,-4.7433,-4.8232,-4.9656,-5.1133,-5.1364,-5.15,-5.1549,-5.1943,-5.1981,-5.2093,-5.2779,-5.2932,-5.3138,-5.5085,-5.5476,-5.5964,-5.6367,-5.688,-5.7043,-5.7279,-5.7383,-5.7639,-5.7976,-5.8194,-5.8218,-5.8254,-5.8576,-5.8675,-5.8675,-5.87,-5.889,-5.8999,-5.9267,-5.9346,-5.961,-5.9713,-5.9881]},{"words":["workers","domestic","migration","labor","home","migrant","immigrant","women","united","immigration","migrants","immigrants","worker","countries","transnational","international","global","conditions","country","labour","union","trade","family","industry","families","foreign","employment","border","economic","asian","philippines","service","factory","employers","children","status","economy","ethnic","filipino","citizenship","paid","research","trafficking","market","jobs","unions","temporary","illegal","mobility","exploitation"],"weights":[-2.7458,-3.629,-3.8025,-4.0221,-4.1976,-4.1987,-4.2526,-4.3255,-4.4345,-4.4643,-4.5405,-4.5576,-4.5647,-4.7249,-4.78,-4.7943,-4.8219,-4.8932,-4.9131,-4.9209,-4.9541,-4.9587,-5.0017,-5.0365,-5.0453,-5.0511,-5.1366,-5.1956,-5.2279,-5.2845,-5.2992,-5.3241,-5.3462,-5.3531,-5.3671,-5.3715,-5.4166,-5.4485,-5.5732,-5.6129,-5.6437,-5.66,-5.6671,-5.6719,-5.717,-5.7245,-5.7655,-5.8124,-5.8207,-5.8473]},{"words":["students","education","studies","teaching","school","faculty","student","college","university","teachers","class","academic","learning","research","courses","program","teacher","educational","schools","curriculum","classroom","programs","issues","women","campus","project","graduate","ing","pedagogy","institutions","teach","quarterly","community","universities","center","experience","colleges","skills","change","tion","diversity","professional","discussion","training","service","literacy","institutional","learn","engineering","classes"],"weights":[-3.0521,-3.4136,-3.5605,-4.2299,-4.2309,-4.2715,-4.3197,-4.3782,-4.412,-4.4831,-4.5372,-4.555,-4.6899,-4.7141,-4.7491,-4.7595,-4.7604,-4.794,-4.8347,-4.8632,-4.9764,-5.0131,-5.1075,-5.1335,-5.2011,-5.2034,-5.2894,-5.2919,-5.4241,-5.4286,-5.4303,-5.4391,-5.5087,-5.5182,-5.5436,-5.6037,-5.6406,-5.7276,-5.7624,-5.7665,-5.7788,-5.7907,-5.7961,-5.8046,-5.8125,-5.8137,-5.8149,-5.8291,-5.8549,-5.8568]},{"words":["women","gender","development","international","rights","world","policy","human","countries","issues","global","equality","economic","organisations","change","research","local","information","ngos","project","training","resources","policies","programme","action","empowerment","national","nations","conference","uk","programmes","access","based","including","education","vol","level","participation","strategies","oxfam","org","projects","impact","support","developing","ngo","process","approach","beijing","governments"],"weights":[-2.5892,-3.1523,-3.2594,-4.155,-4.3107,-4.5666,-4.6401,-4.7279,-4.7349,-4.7829,-4.9635,-5.1821,-5.201,-5.2042,-5.227,-5.2525,-5.259,-5.2647,-5.2659,-5.2674,-5.2747,-5.3114,-5.3818,-5.3998,-5.4088,-5.4088,-5.4182,-5.4281,-5.4369,-5.4714,-5.474,-5.4863,-5.5437,-5.5509,-5.5674,-5.5938,-5.6106,-5.617,-5.6204,-5.6208,-5.6325,-5.6364,-5.6526,-5.7137,-5.7232,-5.726,-5.7322,-5.7404,-5.7419,-5.7438]},{"words":["policy","welfare","government","public","national","programs","support","committee","program","policies","percent","action","federal","act","office","department","report","discrimination","law","council","president","system","reform","staff","legislation","services","administration","united","bill","commission","affirmative","rights","benefits","poor","equal","000","washington","congress","assistance","time","level","legal","plan","decision","association","education","recipients","funding","civil","director"],"weights":[-3.797,-3.8335,-4.3079,-4.3178,-4.3269,-4.5066,-4.5932,-4.6449,-4.6747,-4.6956,-4.7765,-4.7896,-4.8832,-4.9062,-4.9307,-4.9599,-5.0211,-5.0807,-5.0958,-5.1462,-5.1704,-5.2265,-5.2352,-5.2409,-5.2708,-5.3177,-5.3238,-5.3258,-5.4112,-5.4232,-5.444,-5.4808,-5.4898,-5.4994,-5.5028,-5.5544,-5.5782,-5.6261,-5.665,-5.6881,-5.7564,-5.7645,-5.7697,-5.8101,-5.8101,-5.825,-5.8449,-5.8578,-5.8603,-5.8652]},{"words":["reproductive","abortion","women","birth","pregnancy","control","choice","life","rights","reproduction","population","woman","fertility","pregnant","medical","health","pro","technologies","child","fetus","infertility","human","surrogacy","planning","baby","abortions","children","egg","legal","technology","fetal","decision","motherhood","family","law","contraception","genetic","tion","access","childbirth","public","eggs","bodies","maternal","babies","surrogate","debate","prenatal","sperm","donors"],"weights":[-3.2305,-3.3685,-3.5504,-3.9385,-4.0642,-4.2444,-4.276,-4.4385,-4.504,-4.5369,-4.542,-4.5822,-4.5887,-4.6521,-4.6714,-4.6871,-4.7581,-4.7757,-4.7937,-4.9504,-4.9974,-5.0644,-5.1203,-5.1221,-5.1419,-5.1457,-5.1646,-5.1899,-5.1938,-5.1971,-5.2605,-5.3548,-5.3641,-5.3926,-5.4252,-5.4903,-5.4956,-5.51,-5.5245,-5.5656,-5.5742,-5.6125,-5.6185,-5.6691,-5.6733,-5.6818,-5.6959,-5.7223,-5.7234,-5.7358]},{"words":["women","university","studies","feminist","00","paper","research","journal","program","issues","college","book","offers","editor","center","articles","history","information","issue","review","cloth","send","published","box","pages","professor","edited","social","american","mail","books","press","st","philosophy","contact","ba","papers","author","gender","theory","ma","include","volume","special","ny","ca","address","department","york","essays"],"weights":[-3.2589,-3.4625,-3.5755,-4.2162,-4.2236,-4.5581,-4.6766,-4.7098,-4.7652,-4.9719,-4.9778,-4.9804,-5.0859,-5.121,-5.1231,-5.1321,-5.1387,-5.1412,-5.1821,-5.2065,-5.2126,-5.2156,-5.2341,-5.2361,-5.2506,-5.2553,-5.3095,-5.3171,-5.3722,-5.3738,-5.3967,-5.4141,-5.4185,-5.4594,-5.5286,-5.538,-5.5389,-5.5503,-5.5748,-5.5861,-5.5966,-5.5995,-5.6,-5.6053,-5.6092,-5.6826,-5.7037,-5.7085,-5.7161,-5.7172]},{"words":["women","poverty","economic","food","rural","income","poor","household","households","land","development","social","access","urban","production","economy","market","agricultural","agriculture","labour","resources","security","female","money","low","farmers","crisis","people","children","families","employment","time","farm","population","living","countries","financial","services","cent","sector","trade","government","world","growth","increased","cash","headed","bank","debt","rates"],"weights":[-3.4464,-3.6298,-3.7008,-3.9017,-4.0588,-4.1075,-4.1765,-4.2078,-4.4133,-4.4438,-4.7105,-4.7983,-4.8174,-4.8783,-4.9047,-4.9086,-4.9118,-4.9231,-5.1074,-5.1145,-5.1542,-5.1616,-5.2185,-5.2563,-5.2577,-5.2604,-5.2622,-5.2686,-5.2779,-5.3099,-5.319,-5.3589,-5.388,-5.4078,-5.4324,-5.4482,-5.4493,-5.4526,-5.4744,-5.4806,-5.4834,-5.5348,-5.5584,-5.5627,-5.5751,-5.5902,-5.5928,-5.6276,-5.6727,-5.6872]},{"words":["women","muslim","east","jewish","middle","israel","arab","religious","islamic","islam","palestinian","israeli","al","west","german","jews","studies","egypt","western","iran","political","law","public","der","world","veil","germany","egyptian","society","fi","identity","woman","und","iranian","religion","lebanon","turkey","muslims","secular","cultural","countries","berlin","rights","journal","eastern","europe","die","dress","ed","ethnic"],"weights":[-2.5184,-3.7616,-3.7931,-3.8022,-4.0334,-4.263,-4.311,-4.3436,-4.347,-4.4617,-4.4814,-4.518,-4.5962,-4.6124,-4.6469,-4.7309,-4.8579,-4.8712,-4.9825,-4.9911,-5.045,-5.0534,-5.1012,-5.1405,-5.154,-5.1815,-5.2124,-5.285,-5.2947,-5.3264,-5.3477,-5.3706,-5.3854,-5.3886,-5.4191,-5.4279,-5.4527,-5.4793,-5.4852,-5.5163,-5.5649,-5.5675,-5.5713,-5.5843,-5.608,-5.6107,-5.6419,-5.6741,-5.6943,-5.6986]},{"words":["war","military","peace","world","conflict","security","political","international","human","united","national","people","government","violence","nation","post","country","armed","soldiers","refugee","refugees","nuclear","rights","forces","army","civil","anti","wars","defense","camp","asylum","politics","nations","power","camps","news","times","support","weapons","september","combat","struggle","death","front","force","militarism","threat","media","foreign","terror"],"weights":[-2.7861,-3.6186,-3.6422,-4.15,-4.1633,-4.221,-4.2496,-4.3324,-4.3827,-4.5183,-4.6817,-4.8182,-4.8882,-4.8914,-4.9921,-5.0357,-5.0432,-5.0627,-5.0845,-5.0904,-5.1202,-5.1297,-5.1372,-5.1855,-5.1906,-5.3092,-5.3584,-5.3601,-5.3896,-5.4246,-5.4282,-5.4282,-5.4319,-5.458,-5.4589,-5.5043,-5.5162,-5.5845,-5.6429,-5.6498,-5.6705,-5.6811,-5.6858,-5.6918,-5.693,-5.7086,-5.7269,-5.7444,-5.7545,-5.7959]},{"words":["environmental","water","community","environment","justice","communities","climate","change","city","local","nature","people","urban","earth","energy","residents","health","resources","natural","ecological","waste","issues","ecofeminism","planning","transportation","human","public","air","land","ecology","pollution","neighborhood","development","toxic","housing","atlanta","management","project","orleans","plant","sustainable","river","safety","disaster","global","resource","katrina","movement","risk","johnson"],"weights":[-3.1579,-3.4459,-3.9045,-4.0212,-4.0828,-4.2199,-4.2299,-4.3017,-4.436,-4.5491,-4.6037,-4.6302,-4.7185,-4.7821,-4.8596,-4.8596,-4.9302,-4.9412,-4.9847,-5.0423,-5.19,-5.199,-5.202,-5.2461,-5.2637,-5.3097,-5.3379,-5.3598,-5.3822,-5.3886,-5.3913,-5.4024,-5.407,-5.4163,-5.421,-5.5126,-5.5189,-5.5602,-5.5602,-5.5645,-5.57,-5.6022,-5.609,-5.6193,-5.6308,-5.6759,-5.6784,-5.7105,-5.7373,-5.7556]},{"words":["people","time","don","women","feel","woman","life","lives","told","experience","day","community","talk","experiences","lot","didn","sense","ve","personal","friends","interview","stories","money","person","home","interviews","found","class","hard","understand","process","ing","live","story","living","difficult","speak","power","change","participants","left","involved","learn","started","talking","feeling","days","learned","taking","school"],"weights":[-3.511,-4.0561,-4.2798,-4.6274,-4.6468,-4.6586,-4.7062,-4.8051,-4.8349,-4.9561,-5.0048,-5.0132,-5.1035,-5.1209,-5.1907,-5.1936,-5.2255,-5.2436,-5.2775,-5.3111,-5.3326,-5.339,-5.3773,-5.4145,-5.4374,-5.473,-5.5053,-5.5078,-5.5281,-5.5318,-5.5664,-5.5915,-5.6099,-5.6541,-5.6858,-5.6884,-5.6946,-5.7056,-5.7227,-5.7359,-5.7368,-5.7728,-5.7997,-5.8007,-5.8096,-5.818,-5.8361,-5.8654,-5.8727,-5.8838]},{"words":["indian","world","global","cultural","colonial","native","western","indigenous","india","culture","american","transnational","north","nation","people","united","national","cultures","canada","globalization","caribbean","nations","peoples","west","local","international","european","south","land","postcolonial","colonialism","canadian","australian","indians","aboriginal","australia","communities","caste","studies","history","nationalism","ethnic","asian","practices","region","asia","british","america","imperialism","ed"],"weights":[-3.4837,-3.4948,-3.5665,-3.8146,-3.9314,-3.9439,-3.984,-3.9879,-4.0407,-4.2798,-4.4254,-4.4419,-4.5658,-4.5959,-4.624,-4.6637,-4.6967,-4.7031,-4.7332,-4.765,-4.7904,-4.8232,-4.8274,-4.8422,-4.8686,-4.9152,-4.9313,-5.0175,-5.0531,-5.0531,-5.1057,-5.1253,-5.1428,-5.1472,-5.1925,-5.2025,-5.2085,-5.3561,-5.3886,-5.4188,-5.4415,-5.4699,-5.5045,-5.5072,-5.5339,-5.5357,-5.5357,-5.5767,-5.5953,-5.6033]},{"words":["social","political","community","rights","public","politics","citizenship","equality","society","justice","power","participation","communities","people","private","democracy","civil","citizens","individual","liberal","democratic","sphere","based","leadership","institutions","individuals","change","life","process","economic","civic","leaders","equal","citizen","values","collective","action","model","formal","role","issues","identity","diversity","government","freedom","cultural","engagement","exclusion","personal","context"],"weights":[-2.9067,-3.0579,-3.3933,-3.5152,-3.5581,-4.2487,-4.2626,-4.3198,-4.3462,-4.5031,-4.53,-4.573,-4.5814,-4.6293,-4.7034,-4.7267,-4.8238,-4.8757,-4.9601,-4.9947,-5.0079,-5.0934,-5.1594,-5.1653,-5.2273,-5.2422,-5.2477,-5.2573,-5.3002,-5.3649,-5.4434,-5.5018,-5.5214,-5.5299,-5.552,-5.5526,-5.5594,-5.5815,-5.6339,-5.6509,-5.6584,-5.7283,-5.735,-5.766,-5.7745,-5.8027,-5.8343,-5.8425,-5.8483,-5.8685]},{"words":["gender","research","study","social","data","percent","differences","journal","sample","respondents","status","analysis","age","education","findings","survey","significant","found","american","results","income","table","attitudes","effects","sociology","model","variables","al","factors","reported","level","individual","behavior","society","effect","related","researchers","school","college","studies","support","low","influence","characteristics","role","lower","population","levels","participants","suggest"],"weights":[-3.3111,-3.7049,-3.9861,-4.1577,-4.1993,-4.4587,-4.5597,-4.8079,-4.8441,-4.8939,-4.9285,-4.9379,-4.9961,-5.0101,-5.1022,-5.1061,-5.1254,-5.1341,-5.1453,-5.166,-5.1727,-5.185,-5.2128,-5.2286,-5.2417,-5.2599,-5.2734,-5.3053,-5.3057,-5.3313,-5.3759,-5.414,-5.4625,-5.4701,-5.5003,-5.5668,-5.6039,-5.606,-5.6191,-5.6241,-5.6268,-5.6571,-5.6703,-5.6796,-5.6849,-5.717,-5.7194,-5.7225,-5.7347,-5.7465]},{"words":["sexual","sex","lesbian","sexuality","gay","lesbians","male","queer","heterosexual","harassment","female","gender","pornography","masculinity","relationships","prostitution","desire","identity","homosexuality","sexually","love","transgender","heterosexuality","homosexual","relationship","pleasure","orientation","lgbt","people","girls","homophobia","erotic","lesbianism","bisexual","culture","straight","woman","behavior","sexualities","gays","boys","issue","issues","social","trans","prostitutes","intercourse","york","identities","masculine"],"weights":[-2.3158,-2.3496,-3.0221,-3.1337,-3.4022,-3.91,-4.0359,-4.2412,-4.2807,-4.4849,-4.5509,-4.613,-4.7497,-4.7751,-4.803,-4.8106,-4.8604,-4.9591,-4.9753,-4.9974,-5.0528,-5.1134,-5.1766,-5.2353,-5.4037,-5.4686,-5.4928,-5.4937,-5.5205,-5.5292,-5.5312,-5.5361,-5.559,-5.565,-5.6287,-5.632,-5.6473,-5.6774,-5.6819,-5.7465,-5.7773,-5.7861,-5.8195,-5.9225,-5.9504,-5.9654,-5.973,-5.9791,-5.9791,-5.9868]}]}
